{
  // ── Simulation ───────────────────────────────────────────────────────────
  "runs": 1000000,
  "map_iters": 100,
  "map_tolerance": 1e-8,
  
  // ── MAP prior weights ────────────────────────────────────────────────────
  "prior_weight_known": 10.142975,
  "prior_weight_sim":   14.541864,

  // ── Rating initialization & velocity ─────────────────────────────────────
  "initial_white_adv":   66.202862,
  "velocity_time_decay": 0.475789,
  "lookahead_factor":    4.906134,

  // ── Cross-time-control blending ──────────────────────────────────────────
  "rapid_form_weight": -0.493027,
  "blitz_form_weight": -0.497546,
  "color_bleed":       0.182921,

  // ── Draw model (Baseline Nu) ─────────────────────────────────────────────
  "classical_nu": 0.682430,
  "rapid_nu":     0.429082,
  "blitz_nu":     0.260569,

  // ── Hybrid Aggression & Game Theory ──────────────────────────────────────
  "agg_prior_weight":     54.537670,
  "default_aggression_w": 0.636070,
  "default_aggression_b": 0.367663,
  "standings_aggression": 0.179930
}